README.md
setup.py
NEST/__init__.py
NEST/checkArgs.py
NEST/enrichScore.py
NEST/nest.py
NEST/pvalFun.py
NEST/statFun_lm.py
nest_sw.egg-info/PKG-INFO
nest_sw.egg-info/SOURCES.txt
nest_sw.egg-info/dependency_links.txt
nest_sw.egg-info/requires.txt
nest_sw.egg-info/top_level.txt