Metadata-Version: 2.1
Name: nest-sw
Version: 0.1.4
Summary: The Python implementation of the NEST method.
Home-page: https://github.com/smweinst/NEST/tree/main/Python
Author: Sarah Weinsten
Author-email: sarah.m.weinsten@temple.edu
